{
    "type": "FeatureCollection",
    "metadata": {
        "generated": 1587200155000,
        "url": "https://earthquake.usgs.gov/earthquakes/feed/v1.0/summary/significant_month.geojson",
        "title": "USGS Significant Earthquakes, Past Month",
        "status": 200,
        "api": "1.8.1",
        "count": 18
    },
    "features": [
        {
            "type": "Feature",
            "properties": {
                "mag": 6.6,
                "place": "205km W of Chichi-shima, Japan",
                "time": 1587198337501,
                "updated": 1587199899391,
                "tz": 540,
                "url": "https://earthquake.usgs.gov/earthquakes/eventpage/us70008z89",
                "detail": "https://earthquake.usgs.gov/earthquakes/feed/v1.0/detail/us70008z89.geojson",
                "felt": 7,
                "cdi": 2.4,
                "mmi": 0,
                "alert": "green",
                "status": "reviewed",
                "tsunami": 1,
                "sig": 672,
                "net": "us",
                "code": "70008z89",
                "ids": ",at00q8z62q,us70008z89,pt20109000,",
                "sources": ",at,us,pt,",
                "types": ",dyfi,geoserve,impact-link,losspager,origin,phase-data,shakemap,",
                "nst": null,
                "dmin": 1.816,
                "rms": 0.82,
                "gap": 21,
                "magType": "mww",
                "type": "earthquake",
                "title": "M 6.6 - 205km W of Chichi-shima, Japan"
            },
            "geometry": {
                "type": "Point",
                "coordinates": [
                    140.1479,
                    27.1508,
                    458.5
                ]
            },
            "id": "us70008z89"
        },
        {
            "type": "Feature",
            "properties": {
                "mag": 4.19,
                "place": "4km NE of Magna, Utah",
                "time": 1587044489470,
                "updated": 1587198779787,
                "tz": -420,
                "url": "https://earthquake.usgs.gov/earthquakes/eventpage/uu60378837",
                "detail": "https://earthquake.usgs.gov/earthquakes/feed/v1.0/detail/uu60378837.geojson",
                "felt": 6416,
                "cdi": 4.6,
                "mmi": 4.92,
                "alert": "green",
                "status": "reviewed",
                "tsunami": 0,
                "sig": 730,
                "net": "uu",
                "code": "60378837",
                "ids": ",uu60378837,us70008xj0,",
                "sources": ",uu,us,",
                "types": ",dyfi,geoserve,losspager,moment-tensor,origin,phase-data,shakemap,",
                "nst": 52,
                "dmin": 0.02144,
                "rms": 0.16,
                "gap": 32,
                "magType": "ml",
                "type": "earthquake",
                "title": "M 4.2 - 4km NE of Magna, Utah"
            },
            "geometry": {
                "type": "Point",
                "coordinates": [
                    -112.0621667,
                    40.7358333,
                    9.52
                ]
            },
            "id": "uu60378837"
        },
        {
            "type": "Feature",
            "properties": {
                "mag": 5.9,
                "place": "38km ESE of Falam, Burma",
                "time": 1587037523956,
                "updated": 1587124066934,
                "tz": 390,
                "url": "https://earthquake.usgs.gov/earthquakes/eventpage/us70008xhp",
                "detail": "https://earthquake.usgs.gov/earthquakes/feed/v1.0/detail/us70008xhp.geojson",
                "felt": 35,
                "cdi": 5.6,
                "mmi": 6.58,
                "alert": "yellow",
                "status": "reviewed",
                "tsunami": 0,
                "sig": 670,
                "net": "us",
                "code": "70008xhp",
                "ids": ",us70008xhp,",
                "sources": ",us,",
                "types": ",dyfi,geoserve,losspager,moment-tensor,origin,phase-data,shakemap,",
                "nst": null,
                "dmin": 0.416,
                "rms": 0.9,
                "gap": 35,
                "magType": "mww",
                "type": "earthquake",
                "title": "M 5.9 - 38km ESE of Falam, Burma"
            },
            "geometry": {
                "type": "Point",
                "coordinates": [
                    94.0248,
                    22.7822,
                    10
                ]
            },
            "id": "us70008xhp"
        },
        {
            "type": "Feature",
            "properties": {
                "mag": 6,
                "place": "55km NNE of Savannah Bight, Honduras",
                "time": 1587024277597,
                "updated": 1587169883641,
                "tz": -360,
                "url": "https://earthquake.usgs.gov/earthquakes/eventpage/us70008xeb",
                "detail": "https://earthquake.usgs.gov/earthquakes/feed/v1.0/detail/us70008xeb.geojson",
                "felt": 133,
                "cdi": 5.5,
                "mmi": 4.647,
                "alert": "green",
                "status": "reviewed",
                "tsunami": 1,
                "sig": 627,
                "net": "us",
                "code": "70008xeb",
                "ids": ",at00q8vfrr,pt20107000,us70008xeb,",
                "sources": ",at,pt,us,",
                "types": ",dyfi,geoserve,ground-failure,impact-link,losspager,moment-tensor,origin,phase-data,shakemap,",
                "nst": null,
                "dmin": 3.323,
                "rms": 1.45,
                "gap": 31,
                "magType": "mww",
                "type": "earthquake",
                "title": "M 6.0 - 55km NNE of Savannah Bight, Honduras"
            },
            "geometry": {
                "type": "Point",
                "coordinates": [
                    -85.7099,
                    16.9332,
                    10
                ]
            },
            "id": "us70008xeb"
        },
        {
            "type": "Feature",
            "properties": {
                "mag": 4.17,
                "place": "4km ENE of Magna, Utah",
                "time": 1586919369370,
                "updated": 1587174545598,
                "tz": -420,
                "url": "https://earthquake.usgs.gov/earthquakes/eventpage/uu60378292",
                "detail": "https://earthquake.usgs.gov/earthquakes/feed/v1.0/detail/uu60378292.geojson",
                "felt": 9127,
                "cdi": 4.6,
                "mmi": 4.78,
                "alert": "green",
                "status": "reviewed",
                "tsunami": 0,
                "sig": 728,
                "net": "uu",
                "code": "60378292",
                "ids": ",uu60378292,us70008whe,",
                "sources": ",uu,us,",
                "types": ",dyfi,geoserve,losspager,moment-tensor,origin,phase-data,shakemap,",
                "nst": 60,
                "dmin": 0.01793,
                "rms": 0.18,
                "gap": 27,
                "magType": "ml",
                "type": "earthquake",
                "title": "M 4.2 - 4km ENE of Magna, Utah"
            },
            "geometry": {
                "type": "Point",
                "coordinates": [
                    -112.0576667,
                    40.7338333,
                    9.03
                ]
            },
            "id": "uu60378292"
        },
        {
            "type": "Feature",
            "properties": {
                "mag": 5.24,
                "place": "30km SE of Bodie, CA",
                "time": 1586615797040,
                "updated": 1587134806080,
                "tz": -480,
                "url": "https://earthquake.usgs.gov/earthquakes/eventpage/nc73367270",
                "detail": "https://earthquake.usgs.gov/earthquakes/feed/v1.0/detail/nc73367270.geojson",
                "felt": 1720,
                "cdi": 5.6,
                "mmi": 6.76,
                "alert": "green",
                "status": "reviewed",
                "tsunami": 0,
                "sig": 982,
                "net": "nc",
                "code": "73367270",
                "ids": ",nn00721575,nc73367270,us70008tvv,",
                "sources": ",nn,nc,us,",
                "types": ",dyfi,focal-mechanism,geoserve,ground-failure,losspager,moment-tensor,nearby-cities,oaf,origin,phase-data,scitech-link,shake-alert,shakemap,",
                "nst": 46,
                "dmin": 0.268,
                "rms": 0.06,
                "gap": 97,
                "magType": "mw",
                "type": "earthquake",
                "title": "M 5.2 - 30km SE of Bodie, CA"
            },
            "geometry": {
                "type": "Point",
                "coordinates": [
                    -118.7333333,
                    38.0525,
                    8.45
                ]
            },
            "id": "nc73367270"
        },
        {
            "type": "Feature",
            "properties": {
                "mag": 3.5,
                "place": "18km ESE of Anza, CA",
                "time": 1586126238820,
                "updated": 1586598307660,
                "tz": -480,
                "url": "https://earthquake.usgs.gov/earthquakes/eventpage/ci39135575",
                "detail": "https://earthquake.usgs.gov/earthquakes/feed/v1.0/detail/ci39135575.geojson",
                "felt": 1108,
                "cdi": 4.3,
                "mmi": 4.54,
                "alert": null,
                "status": "reviewed",
                "tsunami": 0,
                "sig": 618,
                "net": "ci",
                "code": "39135575",
                "ids": ",ci39135575,us70008pjd,",
                "sources": ",ci,us,",
                "types": ",dyfi,focal-mechanism,geoserve,nearby-cities,origin,phase-data,scitech-link,shakemap,",
                "nst": 141,
                "dmin": 0.06774,
                "rms": 0.21,
                "gap": 28,
                "magType": "mw",
                "type": "earthquake",
                "title": "M 3.5 - 18km ESE of Anza, CA"
            },
            "geometry": {
                "type": "Point",
                "coordinates": [
                    -116.4961667,
                    33.4961667,
                    13.25
                ]
            },
            "id": "ci39135575"
        },
        {
            "type": "Feature",
            "properties": {
                "mag": 3.66,
                "place": "16km ESE of Anza, CA",
                "time": 1585965900170,
                "updated": 1586564525925,
                "tz": -480,
                "url": "https://earthquake.usgs.gov/earthquakes/eventpage/ci39126263",
                "detail": "https://earthquake.usgs.gov/earthquakes/feed/v1.0/detail/ci39126263.geojson",
                "felt": 1022,
                "cdi": 5,
                "mmi": 4.38,
                "alert": null,
                "status": "reviewed",
                "tsunami": 0,
                "sig": 706,
                "net": "ci",
                "code": "39126263",
                "ids": ",ci39126263,us70008n9z,",
                "sources": ",ci,us,",
                "types": ",dyfi,focal-mechanism,geoserve,nearby-cities,origin,phase-data,scitech-link,shakemap,",
                "nst": 145,
                "dmin": 0.06402,
                "rms": 0.2,
                "gap": 23,
                "magType": "mw",
                "type": "earthquake",
                "title": "M 3.7 - 16km ESE of Anza, CA"
            },
            "geometry": {
                "type": "Point",
                "coordinates": [
                    -116.5153333,
                    33.4946667,
                    10.28
                ]
            },
            "id": "ci39126263"
        },
        {
            "type": "Feature",
            "properties": {
                "mag": 4.87,
                "place": "17km ESE of Anza, CA",
                "time": 1585965198920,
                "updated": 1587188531991,
                "tz": -480,
                "url": "https://earthquake.usgs.gov/earthquakes/eventpage/ci39126079",
                "detail": "https://earthquake.usgs.gov/earthquakes/feed/v1.0/detail/ci39126079.geojson",
                "felt": 22181,
                "cdi": 4.8,
                "mmi": 6.52,
                "alert": "green",
                "status": "reviewed",
                "tsunami": 1,
                "sig": 845,
                "net": "ci",
                "code": "39126079",
                "ids": ",ci39126079,at00q88qkv,us70008n9b,",
                "sources": ",ci,at,us,",
                "types": ",dyfi,focal-mechanism,geoserve,impact-link,losspager,moment-tensor,nearby-cities,origin,phase-data,scitech-link,shake-alert,shakemap,",
                "nst": 175,
                "dmin": 0.07088,
                "rms": 0.22,
                "gap": 23,
                "magType": "mw",
                "type": "earthquake",
                "title": "M 4.9 - 17km ESE of Anza, CA"
            },
            "geometry": {
                "type": "Point",
                "coordinates": [
                    -116.5063333,
                    33.4895,
                    10.45
                ]
            },
            "id": "ci39126079"
        },
        {
            "type": "Feature",
            "properties": {
                "mag": 4.8,
                "place": "72km ESE of Cascade, Idaho",
                "time": 1585700861034,
                "updated": 1586891733853,
                "tz": -420,
                "url": "https://earthquake.usgs.gov/earthquakes/eventpage/us70008js1",
                "detail": "https://earthquake.usgs.gov/earthquakes/feed/v1.0/detail/us70008js1.geojson",
                "felt": 533,
                "cdi": 6.6,
                "mmi": 5.691,
                "alert": "green",
                "status": "reviewed",
                "tsunami": 0,
                "sig": 706,
                "net": "us",
                "code": "70008js1",
                "ids": ",ak020485mtmv,us70008js1,mb80387309,",
                "sources": ",ak,us,mb,",
                "types": ",dyfi,geoserve,losspager,moment-tensor,origin,phase-data,shakemap,",
                "nst": null,
                "dmin": 0.935,
                "rms": 0.81,
                "gap": 39,
                "magType": "mww",
                "type": "earthquake",
                "title": "M 4.8 - 72km ESE of Cascade, Idaho"
            },
            "geometry": {
                "type": "Point",
                "coordinates": [
                    -115.1673,
                    44.3232,
                    10
                ]
            },
            "id": "us70008js1"
        },
        {
            "type": "Feature",
            "properties": {
                "mag": 6.5,
                "place": "72km W of Challis, Idaho",
                "time": 1585698751094,
                "updated": 1587179729504,
                "tz": -420,
                "url": "https://earthquake.usgs.gov/earthquakes/eventpage/us70008jr5",
                "detail": "https://earthquake.usgs.gov/earthquakes/feed/v1.0/detail/us70008jr5.geojson",
                "felt": 39137,
                "cdi": 7.6,
                "mmi": 8.239,
                "alert": "green",
                "status": "reviewed",
                "tsunami": 0,
                "sig": 1410,
                "net": "us",
                "code": "70008jr5",
                "ids": ",us70008jr5,mb80387294,uu60371877,",
                "sources": ",us,mb,uu,",
                "types": ",dyfi,finite-fault,general-link,general-text,geoserve,ground-failure,impact-text,losspager,moment-tensor,oaf,origin,phase-data,shakemap,",
                "nst": null,
                "dmin": 0.879,
                "rms": 0.68,
                "gap": 31,
                "magType": "mww",
                "type": "earthquake",
                "title": "M 6.5 - 72km W of Challis, Idaho"
            },
            "geometry": {
                "type": "Point",
                "coordinates": [
                    -115.1356,
                    44.4603,
                    14.53
                ]
            },
            "id": "us70008jr5"
        },
        {
            "type": "Feature",
            "properties": {
                "mag": 3.1,
                "place": "7km NNE of Mascouche, Canada",
                "time": 1585466464294,
                "updated": 1586840171608,
                "tz": -300,
                "url": "https://earthquake.usgs.gov/earthquakes/eventpage/us70008i6u",
                "detail": "https://earthquake.usgs.gov/earthquakes/feed/v1.0/detail/us70008i6u.geojson",
                "felt": 1493,
                "cdi": 4.6,
                "mmi": null,
                "alert": null,
                "status": "reviewed",
                "tsunami": 0,
                "sig": 608,
                "net": "us",
                "code": "70008i6u",
                "ids": ",us70008i6u,",
                "sources": ",us,",
                "types": ",dyfi,geoserve,origin,phase-data,",
                "nst": null,
                "dmin": 0.312,
                "rms": 0.94,
                "gap": 95,
                "magType": "mb_lg",
                "type": "earthquake",
                "title": "M 3.1 - 7km NNE of Mascouche, Canada"
            },
            "geometry": {
                "type": "Point",
                "coordinates": [
                    -73.5734,
                    45.8105,
                    10
                ]
            },
            "id": "us70008i6u"
        },
        {
            "type": "Feature",
            "properties": {
                "mag": 5,
                "place": "41km W of Mentone, Texas",
                "time": 1585235787715,
                "updated": 1587137193344,
                "tz": -360,
                "url": "https://earthquake.usgs.gov/earthquakes/eventpage/us70008ggn",
                "detail": "https://earthquake.usgs.gov/earthquakes/feed/v1.0/detail/us70008ggn.geojson",
                "felt": 2031,
                "cdi": 5.3,
                "mmi": 5.608,
                "alert": "green",
                "status": "reviewed",
                "tsunami": 0,
                "sig": 915,
                "net": "us",
                "code": "70008ggn",
                "ids": ",us70008ggn,",
                "sources": ",us,",
                "types": ",dyfi,general-text,geoserve,ground-failure,losspager,moment-tensor,oaf,origin,phase-data,shakemap,",
                "nst": null,
                "dmin": 0.224,
                "rms": 0.78,
                "gap": 43,
                "magType": "mww",
                "type": "earthquake",
                "title": "M 5.0 - 41km W of Mentone, Texas"
            },
            "geometry": {
                "type": "Point",
                "coordinates": [
                    -104.0386,
                    31.7078,
                    6.64
                ]
            },
            "id": "us70008ggn"
        },
        {
            "type": "Feature",
            "properties": {
                "mag": 7.5,
                "place": "221km SSE of Severo-Kuril'sk, Russia",
                "time": 1585104560896,
                "updated": 1586394371534,
                "tz": 660,
                "url": "https://earthquake.usgs.gov/earthquakes/eventpage/us70008fi4",
                "detail": "https://earthquake.usgs.gov/earthquakes/feed/v1.0/detail/us70008fi4.geojson",
                "felt": 27,
                "cdi": 5.6,
                "mmi": 5.246,
                "alert": "green",
                "status": "reviewed",
                "tsunami": 1,
                "sig": 881,
                "net": "us",
                "code": "70008fi4",
                "ids": ",at00q7qai7,pt20085000,us70008fi4,",
                "sources": ",at,pt,us,",
                "types": ",dyfi,finite-fault,general-text,geoserve,ground-failure,impact-link,losspager,moment-tensor,origin,phase-data,shakemap,",
                "nst": null,
                "dmin": 4.104,
                "rms": 0.67,
                "gap": 12,
                "magType": "mww",
                "type": "earthquake",
                "title": "M 7.5 - 221km SSE of Severo-Kuril'sk, Russia"
            },
            "geometry": {
                "type": "Point",
                "coordinates": [
                    157.6914,
                    48.9688,
                    55.39
                ]
            },
            "id": "us70008fi4"
        },
        {
            "type": "Feature",
            "properties": {
                "mag": 3.94,
                "place": "8km NNE of Magna, Utah",
                "time": 1584926235310,
                "updated": 1587060878035,
                "tz": -420,
                "url": "https://earthquake.usgs.gov/earthquakes/eventpage/uu60369062",
                "detail": "https://earthquake.usgs.gov/earthquakes/feed/v1.0/detail/uu60369062.geojson",
                "felt": 5321,
                "cdi": 4.2,
                "mmi": 4.73,
                "alert": "green",
                "status": "reviewed",
                "tsunami": 0,
                "sig": 659,
                "net": "uu",
                "code": "60369062",
                "ids": ",uu60369062,us70008eak,",
                "sources": ",uu,us,",
                "types": ",dyfi,geoserve,losspager,moment-tensor,origin,phase-data,shakemap,",
                "nst": 44,
                "dmin": 0.01894,
                "rms": 0.19,
                "gap": 52,
                "magType": "ml",
                "type": "earthquake",
                "title": "M 3.9 - 8km NNE of Magna, Utah"
            },
            "geometry": {
                "type": "Point",
                "coordinates": [
                    -112.053,
                    40.779,
                    9.98
                ]
            },
            "id": "uu60369062"
        },
        {
            "type": "Feature",
            "properties": {
                "mag": 5.3,
                "place": "2km WSW of Kasina, Croatia",
                "time": 1584854643700,
                "updated": 1585828841888,
                "tz": 60,
                "url": "https://earthquake.usgs.gov/earthquakes/eventpage/us70008dx7",
                "detail": "https://earthquake.usgs.gov/earthquakes/feed/v1.0/detail/us70008dx7.geojson",
                "felt": 1180,
                "cdi": 7.5,
                "mmi": 7.038,
                "alert": "yellow",
                "status": "reviewed",
                "tsunami": 0,
                "sig": 1400,
                "net": "us",
                "code": "70008dx7",
                "ids": ",us70008dx7,",
                "sources": ",us,",
                "types": ",dyfi,geoserve,impact-text,losspager,moment-tensor,origin,phase-data,shakemap,",
                "nst": null,
                "dmin": 0.794,
                "rms": 0.58,
                "gap": 12,
                "magType": "mww",
                "type": "earthquake",
                "title": "M 5.3 - 2km WSW of Kasina, Croatia"
            },
            "geometry": {
                "type": "Point",
                "coordinates": [
                    15.9697,
                    45.9071,
                    10
                ]
            },
            "id": "us70008dx7"
        },
        {
            "type": "Feature",
            "properties": {
                "mag": 4.5,
                "place": "6km N of Johnson Lane, Nevada",
                "time": 1584754415369,
                "updated": 1587080130444,
                "tz": -480,
                "url": "https://earthquake.usgs.gov/earthquakes/eventpage/nn00719663",
                "detail": "https://earthquake.usgs.gov/earthquakes/feed/v1.0/detail/nn00719663.geojson",
                "felt": 4533,
                "cdi": 5.2,
                "mmi": 5.16,
                "alert": "green",
                "status": "reviewed",
                "tsunami": 0,
                "sig": 832,
                "net": "nn",
                "code": "00719663",
                "ids": ",us70008dbv,nn00719663,",
                "sources": ",us,nn,",
                "types": ",dyfi,geoserve,ground-failure,losspager,moment-tensor,origin,phase-data,shakemap,",
                "nst": 31,
                "dmin": 0.029,
                "rms": 0.1334,
                "gap": 28.07,
                "magType": "ml",
                "type": "earthquake",
                "title": "M 4.5 - 6km N of Johnson Lane, Nevada"
            },
            "geometry": {
                "type": "Point",
                "coordinates": [
                    -119.7361,
                    39.1112,
                    8.4
                ]
            },
            "id": "nn00719663"
        },
        {
            "type": "Feature",
            "properties": {
                "mag": 5.7,
                "place": "23km E of Xegar, China",
                "time": 1584667995479,
                "updated": 1587073158397,
                "tz": 480,
                "url": "https://earthquake.usgs.gov/earthquakes/eventpage/us70008cld",
                "detail": "https://earthquake.usgs.gov/earthquakes/feed/v1.0/detail/us70008cld.geojson",
                "felt": 12,
                "cdi": 8.6,
                "mmi": 6.739,
                "alert": "yellow",
                "status": "reviewed",
                "tsunami": 0,
                "sig": 660,
                "net": "us",
                "code": "70008cld",
                "ids": ",us70008cld,",
                "sources": ",us,",
                "types": ",dyfi,geoserve,losspager,moment-tensor,origin,phase-data,shakemap,",
                "nst": null,
                "dmin": 0.773,
                "rms": 1.01,
                "gap": 18,
                "magType": "mww",
                "type": "earthquake",
                "title": "M 5.7 - 23km E of Xegar, China"
            },
            "geometry": {
                "type": "Point",
                "coordinates": [
                    87.3158,
                    28.5944,
                    10
                ]
            },
            "id": "us70008cld"
        }
    ],
    "bbox": [
        -119.7361,
        16.9332,
        6.64,
        157.6914,
        48.9688,
        458.5
    ]
}